{"data": [{"in_reply_to_user_id": "1566580880", "text": "@AluraOnline não vai sair um plano mensal? quero estudar com vocês mas nem tenho o limite no cartão, aí fica tenso", "id": "1503285485053128707", "public_metrics": {"retweet_count": 0, "reply_count": 1, "like_count": 0, "quote_count": 0}, "created_at": "2022-03-14T08:22:43.000Z", "conversation_id": "1503285485053128707", "author_id": "1004621816399351808"}, {"in_reply_to_user_id": "166308774", "text": "@atila_dev @rodrigobranas @elemarjr @rocketseat @AluraOnline @erickwendel_ Eu acho q não mano. Eu conheço o trabalho dele mais de perto. Óbvio q tem Market, pq é uma empresa, mas isso N significa q ele está enganando alguém", "id": "1503205843411812352", "public_metrics": {"retweet_count": 0, "reply_count": 0, "like_count": 0, "quote_count": 0}, "created_at": "2022-03-14T03:06:15.000Z", "conversation_id": "1502742957459447813", "author_id": "57953637"}, {"text": "Minha irmã de 11 anos diz que eu sou a Entrapta de She-Ra porque faço códigos. E agora eu só aceito ser chamada de Princesa de Dryl 🌌\n\nCc: @mikannn por recomendar @AluraOnline e a série https://t.co/EvrrGLSlLj", "id": "1503203067596099587", "public_metrics": {"retweet_count": 0, "reply_count": 0, "like_count": 0, "quote_count": 0}, "created_at": "2022-03-14T02:55:14.000Z", "conversation_id": "1503203067596099587", "author_id": "1493695702156943362"}, {"text": "continuando os desafios da imersão da @AluraOnline, dessa vez fiz o conversor de temperatura. o input está ocuto e só é exibido após vc escolher qual temperatura irá converter rsrs https://t.co/vRbeBks5Av", "id": "1503186578654613507", "public_metrics": {"retweet_count": 0, "reply_count": 0, "like_count": 1, "quote_count": 0}, "created_at": "2022-03-14T01:49:42.000Z", "conversation_id": "1503186578654613507", "author_id": "1436474896209612804"}, {"in_reply_to_user_id": "1291791121438433282", "text": "@drakenpiece @picpay @blue_edtech_br @Guiabolso @AluraOnline da uma olhadinha aqui pfvr", "id": "1503160348370784259", "public_metrics": {"retweet_count": 0, "reply_count": 0, "like_count": 0, "quote_count": 0}, "created_at": "2022-03-14T00:05:29.000Z", "conversation_id": "1503126689022361602", "author_id": "757771150797733888"}, {"text": "Adivinhe o número secreto. \nhttps://t.co/RnfLPsKI6m\n\nConversor de algumas coisas. \nhttps://t.co/j0p9BvXsHn\n\n@AluraOnline\n#imersaodev #alura", "id": "1503159141107486721", "public_metrics": {"retweet_count": 0, "reply_count": 0, "like_count": 0, "quote_count": 0}, "created_at": "2022-03-14T00:00:41.000Z", "conversation_id": "1503159141107486721", "author_id": "34438472"}, {"text": "Que loucura!\nVendo a aula da @AluraOnline e o rapaz solta: se der 0 eu vou ficar muito feliz, aí apareceu 0 na minha primeira tentativa do código aleatório.\nTo rindo aqui https://t.co/rZLnAFFq95", "id": "1503118292818534411", "public_metrics": {"retweet_count": 0, "reply_count": 0, "like_count": 1, "quote_count": 0}, "created_at": "2022-03-13T21:18:22.000Z", "conversation_id": "1503118292818534411", "author_id": "718591837162889216"}, {"text": "Vai Balboazito e Paulinho de qual livro é essa Frase?\n\n\"Powell soltou um gemido.\n– Por Júpiter! Um robô Descartes!\"\nNome dele é Cutie...\n\n@mauriciojr vc até hj foi o único q citou com detalhes o robô Speedy\n@AluraOnline @paulo_caelum", "id": "1503114376160677895", "public_metrics": {"retweet_count": 0, "reply_count": 1, "like_count": 0, "quote_count": 0}, "created_at": "2022-03-13T21:02:48.000Z", "conversation_id": "1503114376160677895", "author_id": "1036399528998522881"}, {"in_reply_to_user_id": "1566580880", "text": "@AluraOnline Alguma previsao para curso de Blockchain com Solidity?", "id": "1503110493879377933", "public_metrics": {"retweet_count": 0, "reply_count": 0, "like_count": 0, "quote_count": 0}, "created_at": "2022-03-13T20:47:22.000Z", "conversation_id": "1502358757170462728", "author_id": "1035123196540985349"}, {"text": "Imersao dev da @AluraOnline\n\nAluraflix - dia 5 (@ytallodev) https://t.co/926HdF43sg via @CodePen\n\n#bolhadev @sseraphini @APDABot", "id": "1503082196692869124", "public_metrics": {"retweet_count": 0, "reply_count": 0, "like_count": 1, "quote_count": 0}, "created_at": "2022-03-13T18:54:56.000Z", "conversation_id": "1503082196692869124", "author_id": "1260554404605898752"}], "includes": {"users": [{"name": "Alanys 🇦🇹", "username": "alanysguterres", "created_at": "2018-06-07T07:11:20.000Z", "id": "1004621816399351808"}, {"name": "JacobHaru💙", "username": "jacob_moura", "created_at": "2009-07-18T15:16:13.000Z", "id": "57953637"}, {"name": "fernanda;", "username": "techfernandamh", "created_at": "2022-02-15T21:16:31.000Z", "id": "1493695702156943362"}, {"name": "name != number", "username": "thiagothree", "created_at": "2021-09-10T23:41:48.000Z", "id": "1436474896209612804"}, {"name": "may", "username": "imngyeon", "created_at": "2016-07-26T02:54:55.000Z", "id": "757771150797733888"}, {"name": "Leno Silvestre", "username": "leno_o", "created_at": "2009-04-22T23:16:58.000Z", "id": "34438472"}, {"name": "Orange Crush Brasil", "username": "OrangeCrushBr", "created_at": "2016-04-09T00:10:19.000Z", "id": "718591837162889216"}, {"name": "Adv_marinho", "username": "Advmarinho2", "created_at": "2018-09-02T23:44:37.000Z", "id": "1036399528998522881"}, {"name": "Gustavo Sá", "username": "1gustavosa1", "created_at": "2018-08-30T11:12:56.000Z", "id": "1035123196540985349"}, {"name": "Ytallo Bruno", "username": "ytallodev", "created_at": "2020-05-13T12:56:17.000Z", "id": "1260554404605898752"}]}, "meta": {"newest_id": "1503285485053128707", "oldest_id": "1503082196692869124", "result_count": 10, "next_token": "b26v89c19zqg8o3fpyqmi34t8iowbeq8l2n9pdi314ltp"}}
{"data": [{"public_metrics": {"retweet_count": 0, "reply_count": 0, "like_count": 0, "quote_count": 0}, "id": "1503064712585617417", "text": "2/13 da trilha Data Science da @AluraOnline 🤩", "created_at": "2022-03-13T17:45:27.000Z", "conversation_id": "1503064712585617417", "author_id": "1203438944802787329"}, {"public_metrics": {"retweet_count": 0, "reply_count": 1, "like_count": 0, "quote_count": 0}, "id": "1503063919044272128", "in_reply_to_user_id": "57953637", "text": "@jacob_moura @rodrigobranas @elemarjr @rocketseat @AluraOnline @erickwendel_ Acho que essa galera entra no 1% que ele citou.\nE desculpa mas o primo rico é 99% mídia e 1% produto.", "created_at": "2022-03-13T17:42:18.000Z", "conversation_id": "1502742957459447813", "author_id": "166308774"}, {"public_metrics": {"retweet_count": 0, "reply_count": 0, "like_count": 0, "quote_count": 0}, "id": "1502961727968788481", "in_reply_to_user_id": "1243659653734694913", "text": "@Fakefak0s0 @AluraOnline KKKKKKKKKK ok agr mandou bem", "created_at": "2022-03-13T10:56:14.000Z", "conversation_id": "1502818326724104193", "author_id": "139075138"}], "includes": {"users": [{"id": "1203438944802787329", "name": "Coutinho", "username": "ccoutinho_", "created_at": "2019-12-07T22:19:51.000Z"}, {"id": "166308774", "name": "atila.dev ✪", "username": "atila_dev", "created_at": "2010-07-13T21:00:02.000Z"}, {"id": "139075138", "name": "laurao da bateria", "username": "lausmachado", "created_at": "2010-05-01T13:28:22.000Z"}]}, "meta": {"newest_id": "1503064712585617417", "oldest_id": "1502961727968788481", "result_count": 3}}
